gomi/.gitignore
gomi/__about__.py
gomi/__init__.py
gomi/__main__.py
gomi/ajt_japanese_scripts.py
gomi/ankiconnect.py
gomi/common.py
gomi/consts.py
gomi/exporter.py
gomi/importer.py
gomi/overwriter.py
gomi/typing.py
gomi/updater.py
gomi-25.5.3.1.dist-info/METADATA
gomi-25.5.3.1.dist-info/WHEEL
gomi-25.5.3.1.dist-info/entry_points.txt
gomi-25.5.3.1.dist-info/licenses/LICENSE
gomi-25.5.3.1.dist-info/RECORD
