Metadata-Version: 2.4
Name: gomi
Version: 25.5.3.1
Summary: Package to store and manage Note Types for Anki in a git repository.
Project-URL: Documentation, https://github.com/Ajatt-Tools/gomi#readme
Project-URL: Issues, https://github.com/Ajatt-Tools/gomi/issues
Project-URL: Source, https://github.com/Ajatt-Tools/gomi
Author: Ajatt-Tools and contributors
License:                     GNU GENERAL PUBLIC LICENSE
License-File: LICENSE
Classifier: Programming Language :: Python
Classifier: Programming Language :: Python :: 3.12
Classifier: Programming Language :: Python :: 3.13
Classifier: Programming Language :: Python :: Implementation :: CPython
Classifier: Programming Language :: Python :: Implementation :: PyPy
Requires-Python: >=3.12
